apifoncier/__init__.py
apifoncier/cartofriches.py
apifoncier/config.py
apifoncier/dv3f.py
apifoncier/dvf_opendata.py
apifoncier/exceptions.py
apifoncier/ff.py
apifoncier/ind_conso_espace.py
apifoncier/ind_marche.py
apifoncier/ind_prix.py
apifoncier/utils.py
apifoncier-0.0.27.dist-info/LICENSE
apifoncier-0.0.27.dist-info/METADATA
apifoncier-0.0.27.dist-info/WHEEL
apifoncier-0.0.27.dist-info/top_level.txt
apifoncier-0.0.27.dist-info/RECORD
