Metadata-Version: 2.1
Name: apifoncier
Version: 0.0.27
Summary: Mobiliser les données foncières de l'api du Cerema directement avec python
Home-page: https://github.com/rcadot/py.apifoncier
Author: Romain Cadot
Author-email: romain.cadot@cerema.fr
License: MIT
Keywords: api,foncier,cerema,dv3f,friches,artificialisation
Classifier: Programming Language :: Python :: 3
Classifier: License :: OSI Approved :: MIT License
Classifier: Operating System :: OS Independent
Requires-Python: >=3.9
License-File: LICENSE
Requires-Dist: pandas
Requires-Dist: requests
Requires-Dist: geopandas
Requires-Dist: tqdm
Provides-Extra: dev
Requires-Dist: pytest ; extra == 'dev'
